apistar_alembic_migrations/__init__.py
apistar_alembic_migrations-0.0.5.dist-info/DESCRIPTION.rst
apistar_alembic_migrations-0.0.5.dist-info/METADATA
apistar_alembic_migrations-0.0.5.dist-info/RECORD
apistar_alembic_migrations-0.0.5.dist-info/WHEEL
apistar_alembic_migrations-0.0.5.dist-info/metadata.json
apistar_alembic_migrations-0.0.5.dist-info/top_level.txt
