Metadata-Version: 2.0
Name: apistar-alembic-migrations
Version: 0.0.5
Summary: Alembic migrations for apistar
Home-page: https://github.com/colanconnon/apistar_alembic_migrations
Author: Colan Connon
Author-email: cconnon11@gmail.com
License: MIT
Platform: UNKNOWN
Classifier: Development Status :: 3 - Alpha
Classifier: Environment :: Web Environment
Classifier: Intended Audience :: Developers
Classifier: Operating System :: OS Independent
Classifier: Topic :: Internet :: WWW/HTTP
Classifier: Programming Language :: Python :: 3
Classifier: Programming Language :: Python :: 3.5
Classifier: Programming Language :: Python :: 3.6
Requires-Dist: alembic
Requires-Dist: apistar
